prefect_coiled/__init__.py
prefect_coiled/credentials.py
prefect_coiled/worker.py
prefect_coiled/deployments/__init__.py
prefect_coiled/deployments/steps.py
prefect_coiled-0.0.4.dist-info/METADATA
prefect_coiled-0.0.4.dist-info/WHEEL
prefect_coiled-0.0.4.dist-info/entry_points.txt
prefect_coiled-0.0.4.dist-info/licenses/LICENSE
prefect_coiled-0.0.4.dist-info/RECORD
