Metadata-Version: 2.4
Name: prefect-coiled
Version: 0.0.4
Summary: Prefect integrations for interacting with Coiled.
Maintainer-email: Coiled <info@coiled.io>
License: Apache License 2.0
License-File: LICENSE
Keywords: coiled,prefect
Requires-Python: >=3.9
Requires-Dist: coiled>=1.71.1
Requires-Dist: prefect>=3.1.1
